Metadata-Version: 2.1
Name: CombCov
Version: 0.5.1
Summary: Searching for combinatorial covers.
Home-page: https://github.com/PermutaTriangle/CombCov
Author: Permuta Triangle
Author-email: permutatriangle@gmail.com
License: GPL-3
Project-URL: Source, https://github.com/PermutaTriangle/CombCov
Project-URL: Tracker, https://github.com/PermutaTriangle/CombCov/issues
Keywords: combinatorics covers automatic discovery
Platform: UNKNOWN
Classifier: Development Status :: 4 - Beta
Classifier: Intended Audience :: Education
Classifier: Intended Audience :: Science/Research
Classifier: License :: OSI Approved :: GNU General Public License v3 (GPLv3)
Classifier: Programming Language :: Python :: 3.5
Classifier: Programming Language :: Python :: 3.6
Classifier: Programming Language :: Python :: 3.7
Classifier: Programming Language :: Python :: Implementation :: CPython
Classifier: Programming Language :: Python :: Implementation :: PyPy
Classifier: Topic :: Education
Classifier: Topic :: Scientific/Engineering :: Mathematics
Requires-Python: >=3.5
